py_roboat_enviro/__init__.py
py_roboat_enviro/roboat_enviro_backend.py
py_roboat_enviro-0.0.1.dist-info/LICENSE
py_roboat_enviro-0.0.1.dist-info/METADATA
py_roboat_enviro-0.0.1.dist-info/WHEEL
py_roboat_enviro-0.0.1.dist-info/top_level.txt
py_roboat_enviro-0.0.1.dist-info/RECORD
